EnigmaGame/__init__.py
EnigmaGame/__main__.py
EnigmaGame/block.py
EnigmaGame/blocks.py
EnigmaGame/board.py
EnigmaGame/const.py
EnigmaGame/figure.py
EnigmaGame/gpath.py
EnigmaGame-1.0.3.dist-info/LICENSE
EnigmaGame-1.0.3.dist-info/METADATA
EnigmaGame-1.0.3.dist-info/WHEEL
EnigmaGame-1.0.3.dist-info/top_level.txt
EnigmaGame-1.0.3.dist-info/RECORD
