Metadata-Version: 2.1
Name: EnigmaGame
Version: 1.0.3
Summary: A game as difficult as the Rubik’s cube
Author-email: Michael Hodel <info@adiuvaris.ch>
License: MIT License
Project-URL: Homepage, https://github.com/adiuvaris/EnigmaGame
Keywords: Puzzle,Rubick,Turning,Game
Classifier: License :: OSI Approved :: MIT License
Classifier: Programming Language :: Python
Classifier: Programming Language :: Python :: 3
Requires-Python: >=3.9
License-File: LICENSE
Requires-Dist: arcade ==2.6.17
Provides-Extra: dev
Requires-Dist: black ; extra == 'dev'
Requires-Dist: bumpver ; extra == 'dev'
Requires-Dist: isort ; extra == 'dev'
Requires-Dist: pip-tools ; extra == 'dev'
Requires-Dist: pytest ; extra == 'dev'
Requires-Dist: build ; extra == 'dev'
Requires-Dist: twine ; extra == 'dev'
